<?xml version="1.0" encoding="UTF-8"?>
<objects serializationModel="Studio.01.10.00">
    <object class="AudioFile" id="{a692ed60-3fb4-4fc5-807d-3bb8af57a804}">
        <property name="assetPath">
            <value>sfx/Interactors/Glass_Clinking.wav</value>
        </property>
        <property name="frequencyInKHz">
            <value>48</value>
        </property>
        <property name="channelCount">
            <value>1</value>
        </property>
        <property name="length">
            <value>5.6968958333333335</value>
        </property>
        <relationship name="masterAssetFolder">
            <destination>{3fa90b90-a721-4d33-9fad-7f215ad88001}</destination>
        </relationship>
    </object>
</objects>
